cbp/__init__.py
cbp/builder/__init__.py
cbp/builder/base_builder.py
cbp/builder/base_hmmsim_builder.py
cbp/builder/base_simulator.py
cbp/builder/go_simulator.py
cbp/builder/hmm_builder.py
cbp/builder/hmm_engine.py
cbp/builder/hmm_gosim_builder.py
cbp/builder/hmm_sim_builder.py
cbp/builder/hmm_simulator.py
cbp/builder/hmm_zero_builder.py
cbp/builder/line_builder.py
cbp/builder/migr_simulator.py
cbp/builder/migr_visualizer.py
cbp/builder/potential_utils.py
cbp/builder/star_builder.py
cbp/builder/tree_builder.py
cbp/builder/wifi_hmm_builder.py
cbp/builder/wifi_simulator.py
cbp/configs/__init__.py
cbp/configs/base_config.py
cbp/configs/test_config.py
cbp/graph/__init__.py
cbp/graph/base_graph.py
cbp/graph/coef_policy.py
cbp/graph/discrete_graph.py
cbp/graph/go_graph.py
cbp/graph/graph_model.py
cbp/graph/graph_utils.py
cbp/node/__init__.py
cbp/node/base_node.py
cbp/node/discrete_node.py
cbp/node/factor_node.py
cbp/node/go_factor_node.py
cbp/node/go_var_node.py
cbp/node/var_node.py
cbp/utils/__init__.py
cbp/utils/event_utils.py
cbp/utils/message.py
cbp/utils/np_utils.py
pycbp-0.3.1.dist-info/LICENSE
pycbp-0.3.1.dist-info/METADATA
pycbp-0.3.1.dist-info/WHEEL
pycbp-0.3.1.dist-info/top_level.txt
pycbp-0.3.1.dist-info/RECORD
