Metadata-Version: 2.1
Name: pycbp
Version: 0.3.1
Summary: A Library for Constrained Belief Propagation
Home-page: https://github.com/zqsh/cbp
Author: Qinsheng
Author-email: qsh.zh27@gmail.com
License: MIT
Keywords: belief propagation bayesian inference
Platform: UNKNOWN
Classifier: Development Status :: 3 - Alpha
Classifier: Intended Audience :: Science/Research
Classifier: Topic :: Scientific/Engineering :: Artificial Intelligence
Classifier: Topic :: Software Development :: Libraries :: Python Modules
Classifier: License :: OSI Approved :: MIT License
Classifier: Programming Language :: Python :: 3.7
Classifier: Programming Language :: Python :: 3.8
Requires-Python: >=3.7
Requires-Dist: numpy
Requires-Dist: tqdm
Requires-Dist: scipy
Requires-Dist: matplotlib
Requires-Dist: seaborn
Requires-Dist: numba
Requires-Dist: hmmlearn
Provides-Extra: dev
Requires-Dist: Sphinx ; extra == 'dev'
Requires-Dist: sphinx-rtd-theme ; extra == 'dev'
Requires-Dist: nbsphinx ; extra == 'dev'
Requires-Dist: sphinxcontrib-bibtex ; extra == 'dev'
Requires-Dist: pygraphviz ; extra == 'dev'
Requires-Dist: pylint ; extra == 'dev'
Requires-Dist: pytest ; extra == 'dev'
Requires-Dist: pytest-cov ; extra == 'dev'
